{"asset":{"type":"application/si-dpo-3d.document+json","version":"1.0","generator":"Voyager","copyright":"(c) Smithsonian Institution, all rights reserved"},"scene":0,"scenes":[{"units":"mm","nodes":[0,1,6],"meta":0,"setup":0}],"nodes":[{"translation":[-0.4601132,0.7230326,0.5820947],"rotation":[-0.3652539,-0.2976782,-0.1245173,0.8731968],"name":"Camera","camera":0},{"rotation":[0,-0.3226715,0,0.946511],"name":"Lights","children":[2,3,4,5]},{"translation":[-0.6187456,0.6774414,1.1409415],"rotation":[0.4829741,-0.1070728,0.1880998,0.8484633],"scale":[0.2440128,0.2440128,0.2440128],"name":"Key","light":0},{"translation":[1.1149505,0.6591594,0.6825794],"rotation":[0.3546969,0.163893,-0.3861077,0.8356136],"scale":[0.2440128,0.2440128,0.2440128],"name":"Fill #1","light":1},{"translation":[-0.8543491,-1.1172499,0.4066456],"rotation":[0.9374013,-0.3018693,0.0532277,0.1652891],"scale":[0.2440128,0.2440128,0.2440128],"name":"Fill #2","light":2},{"translation":[1.271743,0.0758238,-0.7214158],"rotation":[0.373256,0.6426073,-0.5786063,0.3360813],"scale":[0.2440128,0.2440128,0.2440128],"name":"Rim","light":3},{"name":"Leaf","model":0}],"cameras":[{"type":"perspective","perspective":{"yfov":52,"znear":0.0053448,"zfar":5.3447978},"autoNearFar":true}],"lights":[{"color":[1,0.95,0.9],"intensity":1,"type":"directional","shadowEnabled":true,"shadowSize":2.4401277},{"color":[0.9,0.95,1],"intensity":0.7,"type":"directional","shadowEnabled":true,"shadowSize":2.4401277},{"color":[0.8,0.85,1],"intensity":0.5,"type":"directional"},{"color":[0.85,0.9078313,1],"intensity":0.6,"type":"directional"}],"models":[{"units":"cm","rotation":[0,-0.8304987,0,0.5570206],"boundingBox":{"min":[-0.032399,-0.005604,-0.091825],"max":[0.039776,0.004752,0.095812]},"derivatives":[{"usage":"Web3D","quality":"Medium","assets":[{"uri":"leaf.glb","type":"Model","mimeType":"model/gltf-binary"}]}]}],"metas":[{"collection":{"titles":{"EN":"Leaf"},"intros":{"EN":""}}}],"setups":[{"units":"cm","interface":{"visible":true,"logo":true,"menu":true,"tools":true},"viewer":{"shader":"Default","exposure":1,"gamma":2,"annotationsVisible":false},"reader":{"enabled":false,"position":"Overlay"},"navigation":{"type":"Orbit","enabled":true,"autoZoom":true,"lightsFollowCamera":true,"autoRotation":false,"orbit":{"orbit":[-24,-26,0],"offset":[0,0,150],"minOrbit":[-90,null,null],"maxOrbit":[90,null,null],"minOffset":[null,null,0.1],"maxOffset":[null,null,10000]}},"background":{"style":"RadialGradient","color0":[0.2,0.25,0.3],"color1":[0.01,0.03,0.05]},"floor":{"visible":false,"position":[0,-25,0],"size":50,"color":[0.6,0.75,0.8],"opacity":0.5,"receiveShadow":false},"grid":{"visible":false,"color":[0.5,0.7,0.8]},"tape":{"enabled":false,"startPosition":[0,0,0],"startDirection":[0,0,0],"endPosition":[0,0,0],"endDirection":[0,0,0]},"slicer":{"enabled":false,"axis":"X","inverted":false,"position":0.5}}]}